loading2.py
loading2-0.0.2.dist-info/METADATA
loading2-0.0.2.dist-info/WHEEL
loading2-0.0.2.dist-info/RECORD
