Metadata-Version: 2.4
Name: loading2
Version: 0.0.2
Summary: A simple and elegant Python library for adding loading animations to your functions with a decorator
Project-URL: Homepage, https://github.com/r1cardohj/loading2
Project-URL: Repository, https://github.com/r1cardohj/loading2
Project-URL: Issues, https://github.com/r1cardohj/loading2/issues
Project-URL: Documentation, https://github.com/r1cardohj/loading2#readme
Author-email: r1cardohj <houjun447@gmail.com>
Maintainer-email: r1cardohj <houjun447@gmail.com>
License: MIT
Keywords: animation,decorator,loading,progress,spinner
Classifier: Development Status :: 4 - Beta
Classifier: Intended Audience :: Developers
Classifier: License :: OSI Approved :: MIT License
Classifier: Operating System :: OS Independent
Classifier: Programming Language :: Python :: 3
Classifier: Programming Language :: Python :: 3.12
Classifier: Topic :: Software Development :: Libraries :: Python Modules
Classifier: Topic :: System :: Shells
Classifier: Topic :: Utilities
Requires-Python: >=3.10
Provides-Extra: dev
Requires-Dist: black>=22.0; extra == 'dev'
Requires-Dist: hatchling>=1.0; extra == 'dev'
Requires-Dist: mypy>=1.0; extra == 'dev'
Requires-Dist: pytest-cov>=4.0; extra == 'dev'
Requires-Dist: pytest-mock>=3.10; extra == 'dev'
Requires-Dist: pytest>=7.0; extra == 'dev'
Requires-Dist: ruff>=0.1.0; extra == 'dev'
Provides-Extra: test
Requires-Dist: pytest-cov>=4.0; extra == 'test'
Requires-Dist: pytest-mock>=3.10; extra == 'test'
Requires-Dist: pytest>=7.0; extra == 'test'
